{"config":{"output_file":null,"full_docs":false,"pub_only":true,"reachable_only":true,"distro_crate":false,"signatures":false,"borrow_data":false},"version":"0.18.2","compilation":{"directory":[47,104,111,109,101,47,100,106,47,46,99,97,114,103,111,47,114,101,103,105,115,116,114,121,47,115,114,99,47,103,105,116,104,117,98,46,99,111,109,45,49,101,99,99,54,50,57,57,100,98,57,101,99,56,50,51,47,115,104,114,101,100,45,100,101,114,105,118,101,45,48,46,53,46,49],"program":"/home/dj/.rustup/toolchains/stable-x86_64-unknown-linux-gnu/bin/rls","arguments":["--crate-name","shred_derive","/home/dj/.cargo/registry/src/github.com-1ecc6299db9ec823/shred-derive-0.5.1/src/lib.rs","--color","never","--crate-type","proc-macro","--emit=dep-info,link","-C","prefer-dynamic","-C","debuginfo=2","-C","metadata=87ca8a89c9c1289d","-C","extra-filename=-87ca8a89c9c1289d","--out-dir","/home/dj/Documents/GitHub/carrion-engine/native/target/rls/debug/deps","-L","dependency=/home/dj/Documents/GitHub/carrion-engine/native/target/rls/debug/deps","--extern","proc_macro2=/home/dj/Documents/GitHub/carrion-engine/native/target/rls/debug/deps/libproc_macro2-4f2a89bf1af04da2.rlib","--extern","quote=/home/dj/Documents/GitHub/carrion-engine/native/target/rls/debug/deps/libquote-9da8c6a52f2fdfc4.rlib","--extern","syn=/home/dj/Documents/GitHub/carrion-engine/native/target/rls/debug/deps/libsyn-71423b848d464434.rlib","--cap-lints","allow","--error-format=json","--sysroot","/home/dj/.rustup/toolchains/stable-x86_64-unknown-linux-gnu"],"output":[47,104,111,109,101,47,100,106,47,68,111,99,117,109,101,110,116,115,47,71,105,116,72,117,98,47,99,97,114,114,105,111,110,45,101,110,103,105,110,101,47,110,97,116,105,118,101,47,116,97,114,103,101,116,47,114,108,115,47,100,101,98,117,103,47,100,101,112,115,47,108,105,98,115,104,114,101,100,95,100,101,114,105,118,101,45,56,55,99,97,56,97,56,57,99,57,99,49,50,56,57,100,46,115,111]},"prelude":{"crate_id":{"name":"shred_derive","disambiguator":[3731488844516768514,8728797054126292128]},"crate_root":"/home/dj/.cargo/registry/src/github.com-1ecc6299db9ec823/shred-derive-0.5.1/src","external_crates":[{"file_name":"/home/dj/.cargo/registry/src/github.com-1ecc6299db9ec823/shred-derive-0.5.1/src/lib.rs","num":1,"id":{"name":"std","disambiguator":[1137707474377317163,881293823083572693]}},{"file_name":"/home/dj/.cargo/registry/src/github.com-1ecc6299db9ec823/shred-derive-0.5.1/src/lib.rs","num":2,"id":{"name":"core","disambiguator":[16254816028303588237,6669189139375923666]}},{"file_name":"/home/dj/.cargo/registry/src/github.com-1ecc6299db9ec823/shred-derive-0.5.1/src/lib.rs","num":3,"id":{"name":"compiler_builtins","disambiguator":[7111806954579578569,2199841390691958019]}},{"file_name":"/home/dj/.cargo/registry/src/github.com-1ecc6299db9ec823/shred-derive-0.5.1/src/lib.rs","num":4,"id":{"name":"rustc_std_workspace_core","disambiguator":[6021837240640825503,11520007856923678909]}},{"file_name":"/home/dj/.cargo/registry/src/github.com-1ecc6299db9ec823/shred-derive-0.5.1/src/lib.rs","num":5,"id":{"name":"alloc","disambiguator":[12444724012878050064,2416873571855687959]}},{"file_name":"/home/dj/.cargo/registry/src/github.com-1ecc6299db9ec823/shred-derive-0.5.1/src/lib.rs","num":6,"id":{"name":"libc","disambiguator":[6979589238717360547,5382701582921578244]}},{"file_name":"/home/dj/.cargo/registry/src/github.com-1ecc6299db9ec823/shred-derive-0.5.1/src/lib.rs","num":7,"id":{"name":"unwind","disambiguator":[14383072016947483551,11019396538837452451]}},{"file_name":"/home/dj/.cargo/registry/src/github.com-1ecc6299db9ec823/shred-derive-0.5.1/src/lib.rs","num":8,"id":{"name":"rustc_demangle","disambiguator":[15664728184530138178,15668582881963515515]}},{"file_name":"/home/dj/.cargo/registry/src/github.com-1ecc6299db9ec823/shred-derive-0.5.1/src/lib.rs","num":9,"id":{"name":"backtrace_sys","disambiguator":[16547370833325286379,14798728708606514427]}},{"file_name":"/home/dj/.cargo/registry/src/github.com-1ecc6299db9ec823/shred-derive-0.5.1/src/lib.rs","num":10,"id":{"name":"panic_unwind","disambiguator":[3405404226459150258,2890948387317429027]}},{"file_name":"/home/dj/.cargo/registry/src/github.com-1ecc6299db9ec823/shred-derive-0.5.1/src/lib.rs","num":11,"id":{"name":"proc_macro","disambiguator":[5071772555373616602,3347016914639171079]}},{"file_name":"/home/dj/.cargo/registry/src/github.com-1ecc6299db9ec823/shred-derive-0.5.1/src/lib.rs","num":12,"id":{"name":"proc_macro2","disambiguator":[13735570248750286767,378713339636373599]}},{"file_name":"/home/dj/.cargo/registry/src/github.com-1ecc6299db9ec823/shred-derive-0.5.1/src/lib.rs","num":13,"id":{"name":"unicode_xid","disambiguator":[17149669904321865303,12118467881816477010]}},{"file_name":"/home/dj/.cargo/registry/src/github.com-1ecc6299db9ec823/shred-derive-0.5.1/src/lib.rs","num":14,"id":{"name":"quote","disambiguator":[11786382326626864249,4666284659084996843]}},{"file_name":"/home/dj/.cargo/registry/src/github.com-1ecc6299db9ec823/shred-derive-0.5.1/src/lib.rs","num":15,"id":{"name":"syn","disambiguator":[13647056676225923594,16269550692022021591]}}],"span":{"file_name":[47,104,111,109,101,47,100,106,47,46,99,97,114,103,111,47,114,101,103,105,115,116,114,121,47,115,114,99,47,103,105,116,104,117,98,46,99,111,109,45,49,101,99,99,54,50,57,57,100,98,57,101,99,56,50,51,47,115,104,114,101,100,45,100,101,114,105,118,101,45,48,46,53,46,49,47,115,114,99,47,108,105,98,46,114,115],"byte_start":0,"byte_end":4227,"line_start":1,"line_end":148,"column_start":1,"column_end":2}},"imports":[],"defs":[{"kind":"Mod","id":{"krate":0,"index":0},"span":{"file_name":[47,104,111,109,101,47,100,106,47,46,99,97,114,103,111,47,114,101,103,105,115,116,114,121,47,115,114,99,47,103,105,116,104,117,98,46,99,111,109,45,49,101,99,99,54,50,57,57,100,98,57,101,99,56,50,51,47,115,104,114,101,100,45,100,101,114,105,118,101,45,48,46,53,46,49,47,115,114,99,47,108,105,98,46,114,115],"byte_start":0,"byte_end":4227,"line_start":1,"line_end":148,"column_start":1,"column_end":2},"name":"","qualname":"::","value":"/home/dj/.cargo/registry/src/github.com-1ecc6299db9ec823/shred-derive-0.5.1/src/lib.rs","parent":null,"children":[{"krate":0,"index":2},{"krate":0,"index":4},{"krate":0,"index":6},{"krate":0,"index":8},{"krate":0,"index":10},{"krate":0,"index":12},{"krate":0,"index":14},{"krate":0,"index":16},{"krate":0,"index":18},{"krate":0,"index":20},{"krate":0,"index":46},{"krate":0,"index":48},{"krate":0,"index":50},{"krate":0,"index":52},{"krate":0,"index":54},{"krate":0,"index":56},{"krate":0,"index":60}],"decl_id":null,"docs":"","sig":null,"attributes":[{"value":"recursion_limit = \"256\"","span":{"file_name":[47,104,111,109,101,47,100,106,47,46,99,97,114,103,111,47,114,101,103,105,115,116,114,121,47,115,114,99,47,103,105,116,104,117,98,46,99,111,109,45,49,101,99,99,54,50,57,57,100,98,57,101,99,56,50,51,47,115,104,114,101,100,45,100,101,114,105,118,101,45,48,46,53,46,49,47,115,114,99,47,108,105,98,46,114,115],"byte_start":0,"byte_end":27,"line_start":1,"line_end":1,"column_start":1,"column_end":28}}]},{"kind":"Function","id":{"krate":0,"index":46},"span":{"file_name":[47,104,111,109,101,47,100,106,47,46,99,97,114,103,111,47,114,101,103,105,115,116,114,121,47,115,114,99,47,103,105,116,104,117,98,46,99,111,109,45,49,101,99,99,54,50,57,57,100,98,57,101,99,56,50,51,47,115,104,114,101,100,45,100,101,114,105,118,101,45,48,46,53,46,49,47,115,114,99,47,108,105,98,46,114,115],"byte_start":467,"byte_end":478,"line_start":20,"line_end":20,"column_start":8,"column_end":19},"name":"system_data","qualname":"::system_data","value":"fn (input: TokenStream) -> TokenStream","parent":null,"children":[],"decl_id":null,"docs":" Used to `#[derive]` the trait `SystemData`.\n","sig":null,"attributes":[{"value":"proc_macro_derive(SystemData)","span":{"file_name":[47,104,111,109,101,47,100,106,47,46,99,97,114,103,111,47,114,101,103,105,115,116,114,121,47,115,114,99,47,103,105,116,104,117,98,46,99,111,109,45,49,101,99,99,54,50,57,57,100,98,57,101,99,56,50,51,47,115,104,114,101,100,45,100,101,114,105,118,101,45,48,46,53,46,49,47,115,114,99,47,108,105,98,46,114,115],"byte_start":427,"byte_end":459,"line_start":19,"line_end":19,"column_start":1,"column_end":33}}]}],"impls":[],"refs":[],"macro_refs":[],"relations":[]}